slurm_usage.py
slurm_usage-3.1.0.dist-info/METADATA
slurm_usage-3.1.0.dist-info/WHEEL
slurm_usage-3.1.0.dist-info/entry_points.txt
slurm_usage-3.1.0.dist-info/licenses/LICENSE
slurm_usage-3.1.0.dist-info/RECORD
