Metadata-Version: 2.4
Name: slurm-usage
Version: 3.1.0
Summary: Command to list the current cluster usage per user.
Project-URL: Homepage, https://github.com/basnijholt/slurm-usage
Author-email: Bas Nijholt <bas@nijho.lt>
License: MIT
License-File: LICENSE
Requires-Python: >=3.10
Requires-Dist: polars>=1.8.2
Requires-Dist: pydantic>=2.10.6
Requires-Dist: pyyaml>=6.0.2
Requires-Dist: rich
Requires-Dist: typer>=0.16.1
Provides-Extra: docs
Provides-Extra: test
Requires-Dist: coverage; extra == 'test'
Requires-Dist: pre-commit; extra == 'test'
Requires-Dist: pytest; extra == 'test'
Requires-Dist: pytest-cov; extra == 'test'
